distributed_worker/__init__.py
distributed_worker/manager.py
distributed_worker/worker.py
distributed_worker-1.3.2.dist-info/LICENSE
distributed_worker-1.3.2.dist-info/METADATA
distributed_worker-1.3.2.dist-info/WHEEL
distributed_worker-1.3.2.dist-info/top_level.txt
distributed_worker-1.3.2.dist-info/RECORD
