Metadata-Version: 2.1
Name: distributed-worker
Version: 1.3.2
Summary: A Python wrapper around multiprocessing for easy cross-machine computation 
Home-page: https://github.com/i404788/distributed-worker
Author: Casper
Author-email: casper@devdroplets.com
License: BSD 2-Clause "Simplified" License
Platform: UNKNOWN
Classifier: Development Status :: 3 - Alpha
Classifier: Intended Audience :: Developers
Classifier: License :: OSI Approved :: BSD License
Classifier: Programming Language :: Python :: 3
Classifier: Programming Language :: Python :: 3.5
Classifier: Programming Language :: Python :: 3.6
Classifier: Programming Language :: Python :: 3.7
Classifier: Programming Language :: Python :: 3.8
